odoo/addons/sale_quotation_builder/README.rst
odoo/addons/sale_quotation_builder/__init__.py
odoo/addons/sale_quotation_builder/__manifest__.py
odoo/addons/sale_quotation_builder/hooks.py
odoo/addons/sale_quotation_builder/controllers/__init__.py
odoo/addons/sale_quotation_builder/controllers/main.py
odoo/addons/sale_quotation_builder/data/sale_order_template_data.xml
odoo/addons/sale_quotation_builder/i18n/af.po
odoo/addons/sale_quotation_builder/i18n/am.po
odoo/addons/sale_quotation_builder/i18n/ar.po
odoo/addons/sale_quotation_builder/i18n/az.po
odoo/addons/sale_quotation_builder/i18n/be.po
odoo/addons/sale_quotation_builder/i18n/bg.po
odoo/addons/sale_quotation_builder/i18n/bs.po
odoo/addons/sale_quotation_builder/i18n/ca.po
odoo/addons/sale_quotation_builder/i18n/cs.po
odoo/addons/sale_quotation_builder/i18n/da.po
odoo/addons/sale_quotation_builder/i18n/de.po
odoo/addons/sale_quotation_builder/i18n/el.po
odoo/addons/sale_quotation_builder/i18n/es.po
odoo/addons/sale_quotation_builder/i18n/es_MX.po
odoo/addons/sale_quotation_builder/i18n/et.po
odoo/addons/sale_quotation_builder/i18n/fa.po
odoo/addons/sale_quotation_builder/i18n/fi.po
odoo/addons/sale_quotation_builder/i18n/fr.po
odoo/addons/sale_quotation_builder/i18n/gu.po
odoo/addons/sale_quotation_builder/i18n/he.po
odoo/addons/sale_quotation_builder/i18n/hi.po
odoo/addons/sale_quotation_builder/i18n/hr.po
odoo/addons/sale_quotation_builder/i18n/hu.po
odoo/addons/sale_quotation_builder/i18n/hy.po
odoo/addons/sale_quotation_builder/i18n/id.po
odoo/addons/sale_quotation_builder/i18n/is.po
odoo/addons/sale_quotation_builder/i18n/it.po
odoo/addons/sale_quotation_builder/i18n/ja.po
odoo/addons/sale_quotation_builder/i18n/km.po
odoo/addons/sale_quotation_builder/i18n/ko.po
odoo/addons/sale_quotation_builder/i18n/lb.po
odoo/addons/sale_quotation_builder/i18n/lo.po
odoo/addons/sale_quotation_builder/i18n/lt.po
odoo/addons/sale_quotation_builder/i18n/lv.po
odoo/addons/sale_quotation_builder/i18n/ml.po
odoo_addon_sale_quotation_builder-17.0.1.0.1.2.dist-info/METADATA
odoo_addon_sale_quotation_builder-17.0.1.0.1.2.dist-info/WHEEL
odoo_addon_sale_quotation_builder-17.0.1.0.1.2.dist-info/top_level.txt
odoo_addon_sale_quotation_builder-17.0.1.0.1.2.dist-info/RECORD
