Metadata-Version: 2.1
Name: odoo-addon-sale_quotation_builder
Version: 17.0.1.0.1.2
Requires-Python: >=3.10
Requires-Dist: odoo>=17.0a,<17.1dev
Summary: Build great quotation templates
Home-page: https://github.com/OCA/sale-reporting
License: LGPL-3
Author: Odoo Community Association (OCA), Odoo SA
Author-email: support@odoo-community.org
Classifier: Programming Language :: Python
Classifier: Framework :: Odoo
Classifier: Framework :: Odoo :: 17.0
Classifier: License :: OSI Approved :: GNU Lesser General Public License v3 (LGPLv3)
